msaccessdb/__init__.py
msaccessdb/create.py
msaccessdb/msaccessdb.py
msaccessdb-1.0.0.dist-info/LICENSE
msaccessdb-1.0.0.dist-info/METADATA
msaccessdb-1.0.0.dist-info/WHEEL
msaccessdb-1.0.0.dist-info/top_level.txt
msaccessdb-1.0.0.dist-info/RECORD
