Metadata-Version: 2.1
Name: msaccessdb
Version: 1.0.0
Summary: Create a new empty Access database
Home-page: https://github.com/gordthompson/msaccessdb
Author: Gord Thompson
Author-email: gord@gordthompson.com
License: Apache-2.0
Keywords: Microsoft Access
Platform: UNKNOWN
Classifier: Development Status :: 5 - Production/Stable
Classifier: Intended Audience :: Developers
Classifier: Programming Language :: Python :: 3
Classifier: License :: OSI Approved :: Apache Software License
Classifier: Operating System :: OS Independent
